[
    {
      "name": "iPhone 13 Pro",
      "price": "999.00",
      "image": "https://images.pexels.com/photos/12582008/pexels-photo-12582008.jpeg?auto=compress&cs=tinysrgb&w=1260&h=750&dpr=1",
      "added_to_cart": false
    },
    {
      "name":"Samsung Galaxy S21 Ultra",
      "price": "1199.99",
      "image": "https://images.samsung.com/is/image/samsung/p6pim/levant/galaxy-s21/gallery/levant-galaxy-s21-ultra-5g-g988-371058-sm-g998bzkgmea-thumb-368334301?imwidth=720",
      "added_to_cart": false
    },
    {
      "name": "MacBook Pro M1",
      "price": "1299.00",
      "image": "https://store.storeimages.cdn-apple.com/4982/as-images.apple.com/is/mbp-spacegray-select-202011_GEO_US?wid=892&hei=820&&qlt=80&.v=1603406905000",
      "added_to_cart": false
    },
    {
      "name": "Sony WH-1000XM4",
      "price": "349.99",
      "image": "http://media.4rgos.it/s/Argos/8136983_R_SET?$Main768$&w=620&h=620",
      "added_to_cart": false
    },
    {
      "name": "Nintendo Switch OLED Model",
      "price": "349.99",
      "image": "https://assets.nintendo.com/image/upload/f_auto/q_auto/c_fill,w_300/ncom/en_US/switch/site-design-update/hardware-hero-combo",
      "added_to_cart": false
    },
    {
      "name": "Canon EOS R5",
      "price": "3899.00",
      "image": "https://amateurphotographer.com/wp-content/uploads/sites/7/2022/08/CanonEOSR5_online1.jpg",
      "added_to_cart": false
    }
  ]